{
  "title": "Кот Шрёдингера [MinutePhysics]",
  "content": "\n            Название: Кот Шрёдингера [MinutePhysics]\n            \n            Описание:\n            Проект «Минута физики» популярно описывает явления и загадки мира физики. \n\nВ этом эпизоде речь пойдет о коте Шрёдингера, о природе «квантовой запутанности» и о нашем восприятии реальности. \n\nПри создании ролика ни один кот не пострадал.\n\nРедактура: Розалия Атняшева\nОзвучка: Руслан Романов\nМонтаж: Руслан Романов \nОбложка: Софья Зозуля\n\nИсточник: https://youtu.be/IOYyCHGWJq4\n© https://www.youtube.com/user/minutephysics \n\nПереведено и озвучено: vertdider.com\n            \n            Длительность: 103 секунд\n            \n            Теги: физика, научно-популярное, исследование, vertdider, vert_dider, vert-dider, vert dider, Schrödinger's Cat, Physics (Field Of Study), кот шредингера, квантовая запутанность, мульивселенная, частица, элементарная, протон, ядро, нейтрон\n            ",
  "categories": [
    "vert_dider",
    "научно-популярное",
    "физика",
    "исследование",
    "vert dider",
    "кот шредингера",
    "Schrödinger's Cat",
    "vertdider",
    "мульивселенная",
    "ядро",
    "нейтрон",
    "Physics (Field Of Study)",
    "элементарная",
    "vert-dider",
    "квантовая запутанность",
    "протон",
    "частица"
  ],
  "processed_categories": [
    "исследование",
    "наука",
    "vert-dider",
    "квантовая запутанность",
    "физика",
    "мульивселенная",
    "ядро",
    "Physics (Field Of Study)",
    "протон",
    "vert_dider",
    "научно-популярное",
    "vert dider",
    "кот шредингера",
    "Schrödinger's Cat",
    "vertdider",
    "элементарная",
    "образование",
    "частица",
    "нейтрон"
  ],
  "simplified_content": "• Название: Кот Шрёдингера [MinutePhysics] Описание: Проект «Минута физики» популярно описывает\n• явления и загадки мира физики\n• В этом эпизоде речь пойдет о коте Шрёдингера, о природе\n• «квантовой запутанности» и о нашем восприятии реальности\n• При создании ролика ни один кот не пострадал\n• Редактура: Розалия Атняшева Озвучка: Руслан Романов Монтаж: Руслан Романов Обложка:\n• Софья Зозуля Источник: https://youtu\n• be/IOYyCHGWJq4\n© https://www\n• youtube\n• com/user/minutephysics \n\nПереведено и озвучено: vertdider\n• com Длительность: 103 секунд Теги: физика, научно-популярное, исследование, vertdider, vert_dider,\n• vert-dider, vert dider, Schrödinger's Cat, Physics (Field Of Study), кот\n• шредингера, квантовая запутанность, мульивселенная, частица, элементарная, протон, ядро, нейтрон",
  "term_explanations": {
    "terms": []
  },
  "visualizations": {
    "типы_визуализаций": [
      {
        "тип": "схема",
        "название": "Основная структура",
        "элементы": [
          {
            "уровень": 1,
            "текст": "Кот Шрёдингера [MinutePhysics]"
          },
          {
            "уровень": 2,
            "текст": "Основное содержание"
          }
        ]
      }
    ]
  },
  "learning_aids": {
    "questions": [
      {
        "question": "How would you apply Название: Кот Шрёдингера in practice?",
        "options": [
          "кот шредингера, квантовая",
          "Название: Кот Шрёдингера",
          "нейтрон",
          "элементарная, протон, ядро,"
        ],
        "correct_answer": "Название: Кот Шрёдингера"
      },
      {
        "question": "How would you apply [MinutePhysics] Описание: Проект in practice?",
        "options": [
          "коте Шрёдингера, о",
          "[MinutePhysics] Описание: Проект",
          "восприятии реальности. При",
          "В этом эпизоде"
        ],
        "correct_answer": "[MinutePhysics] Описание: Проект"
      },
      {
        "question": "Which of the following best describes «Минута физики» популярно?",
        "options": [
          "и о нашем",
          "создании ролика ни",
          "(Field Of Study),",
          "«Минута физики» популярно"
        ],
        "correct_answer": "«Минута физики» популярно"
      }
    ]
  },
  "processed_at": "2025-03-10T21:37:08.247455",
  "visualization_paths": {
    "Основная структура": "visualizations\\основная_структура.txt"
  }
}